LICENSE.txt
MANIFEST.in
README.rst
setup.py
codedeploy_monitor/__init__.py
codedeploy_monitor/config.py
codedeploy_monitor/config_parser.py
codedeploy_monitor/deploy_utils.py
codedeploy_monitor/exceptions.py
codedeploy_monitor/main_app.py
codedeploy_monitor.egg-info/PKG-INFO
codedeploy_monitor.egg-info/SOURCES.txt
codedeploy_monitor.egg-info/dependency_links.txt
codedeploy_monitor.egg-info/entry_points.txt
codedeploy_monitor.egg-info/requires.txt
codedeploy_monitor.egg-info/top_level.txt