Metadata-Version: 1.1
Name: codedeploy-monitor
Version: 0.1
Summary: Creates and monitors AWS CodeDeploy deployments.
Home-page: http://github.com/headincloud/codedeploy_monitor
Author: Jeroen Jacobs
Author-email: info@headincloud.be
License: GPLv3
Keywords: aws,codedeploy
Platform: UNKNOWN
Classifier: Development Status :: 2 - Pre-Alpha
Classifier: Environment :: Console
Classifier: Intended Audience :: Developers
Classifier: Intended Audience :: System Administrators
Classifier: License :: OSI Approved :: GNU General Public License v3 (GPLv3)
Classifier: Operating System :: POSIX :: Linux
Classifier: Operating System :: MacOS :: MacOS X
Classifier: Programming Language :: Python :: 2.7
Classifier: Programming Language :: Python :: 3.2
Classifier: Programming Language :: Python :: 3.3
Classifier: Programming Language :: Python :: 3.4
Classifier: Programming Language :: Python :: 3.5
Classifier: Topic :: System :: Software Distribution
